taipan_di/__init__.py
taipan_di/classes/__init__.py
taipan_di/classes/registerers/__init__.py
taipan_di/classes/registerers/factory_registerer.py
taipan_di/classes/registerers/pipeline_registerer.py
taipan_di/classes/registerers/service_registerer.py
taipan_di/classes/registerers/singleton_registerer.py
taipan_di/classes/scopes/__init__.py
taipan_di/classes/scopes/factory_scope.py
taipan_di/classes/scopes/singleton_scope.py
taipan_di/classes/service_collection.py
taipan_di/classes/service_container.py
taipan_di/classes/service_provider.py
taipan_di/classes/tools/__init__.py
taipan_di/classes/tools/instanciate_service.py
taipan_di/classes/tools/pipeline_factory.py
taipan_di/classes/tools/pipeline_link.py
taipan_di/errors/__init__.py
taipan_di/errors/taipan_error.py
taipan_di/errors/taipan_injection_error.py
taipan_di/errors/taipan_registration_error.py
taipan_di/errors/taipan_resolution_error.py
taipan_di/errors/taipan_unregistered_error.py
taipan_di/interfaces/__init__.py
taipan_di/interfaces/base_scope.py
taipan_di/interfaces/base_service_container.py
taipan_di/interfaces/base_service_provider.py
taipan_di/py.typed
taipan_di-0.0.7.dist-info/LICENSE
taipan_di-0.0.7.dist-info/METADATA
taipan_di-0.0.7.dist-info/WHEEL
taipan_di-0.0.7.dist-info/RECORD
