Metadata-Version: 2.1
Name: taipan-di
Version: 0.0.7
Summary: Truly Amazing Inversion of control Python library Analogous to .Net's DI
Home-page: https://github.com/Billuc/Taipan-DI
License: MIT
Keywords: taipan,dependency injection,dependency,python
Author: Billuc
Author-email: billuc@hotmail.fr
Requires-Python: >=3.9,<4.0
Classifier: License :: OSI Approved :: MIT License
Classifier: Programming Language :: Python :: 3
Classifier: Programming Language :: Python :: 3.9
Classifier: Programming Language :: Python :: 3.10
Classifier: Programming Language :: Python :: 3.11
Classifier: Topic :: Software Development :: Libraries
Classifier: Topic :: Software Development :: Libraries :: Python Modules
Requires-Dist: typing-extensions (>=4.6.0,<5.0.0)
Project-URL: Documentation, https://github.com/Billuc/Taipan-DI
Project-URL: Repository, https://github.com/Billuc/Taipan-DI
